CHANGES.txt
LICENSE.txt
MANIFEST.in
README.txt
setup.py
src/m01/__init__.py
src/m01.publisher.egg-info/PKG-INFO
src/m01.publisher.egg-info/SOURCES.txt
src/m01.publisher.egg-info/dependency_links.txt
src/m01.publisher.egg-info/entry_points.txt
src/m01.publisher.egg-info/namespace_packages.txt
src/m01.publisher.egg-info/not-zip-safe
src/m01.publisher.egg-info/requires.txt
src/m01.publisher.egg-info/top_level.txt
src/m01/publisher/__init__.py
src/m01/publisher/absoluteurl.zcml
src/m01/publisher/application.py
src/m01/publisher/configure.zcml
src/m01/publisher/debug.py
src/m01/publisher/interfaces.py
src/m01/publisher/namespace.zcml
src/m01/publisher/publication.py
src/m01/publisher/publish.py
src/m01/publisher/publisher.py
src/m01/publisher/publisher.zcml
src/m01/publisher/testing.py
src/m01/publisher/traverser.zcml
src/m01/publisher/wsgi.py
src/m01/publisher/schema/productconfig.xml
src/m01/publisher/schema/schema.xml